cvemanager/__init__.py
cvemanager/cve_dbms.py
cvemanager/cve_manager.py
cvemanager/main.py
tests/__init__.py
tests/test_dbms.py
tests/test_manager.py
cvemanager-0.0.6.dist-info/LICENCE
cvemanager-0.0.6.dist-info/METADATA
cvemanager-0.0.6.dist-info/WHEEL
cvemanager-0.0.6.dist-info/entry_points.txt
cvemanager-0.0.6.dist-info/top_level.txt
cvemanager-0.0.6.dist-info/RECORD
