Metadata-Version: 2.1
Name: cvemanager
Version: 0.0.6
Summary: A script for managing cves
Home-page: https://github.com/gaborantal/cve_manager
Author: Gabor Antal
Author-email: antalgabor1993@gmail.com
License: UNKNOWN
Platform: UNKNOWN
Classifier: Programming Language :: Python :: 3
Classifier: Operating System :: OS Independent
Requires-Python: >=3.6
